peropq/__init__.py
peropq/bch_optimized.py
peropq/commutators_bitstrings.py
peropq/ed_module.py
peropq/exact_diagonalization.py
peropq/exact_norm.py
peropq/hamiltonian.py
peropq/optimizer.py
peropq/pauli_bitstring.py
peropq/unconstrained_variational_unitary.py
peropq/variational_unitary.py
peropq-0.2.0.dist-info/LICENSE
peropq-0.2.0.dist-info/METADATA
peropq-0.2.0.dist-info/WHEEL
peropq-0.2.0.dist-info/RECORD
