Metadata-Version: 2.1
Name: PerOpQ
Version: 0.2.0
Summary: 
Author: Travis Thompson
Author-email: travis.thompson@quantinuum.com
Requires-Python: >=3.10,<4.0
Classifier: Programming Language :: Python :: 3
Classifier: Programming Language :: Python :: 3.10
Classifier: Programming Language :: Python :: 3.11
Classifier: Programming Language :: Python :: 3.12
Requires-Dist: numba (>=0.60.0,<0.61.0)
Requires-Dist: numpy (>=1.26,<1.27)
Requires-Dist: rich (>=13.8.1,<13.9.0)
Requires-Dist: scipy (>=1.11.3,<2.0.0)
Project-URL: Documentation, https://peropq.readthedocs.io
